Round_Robin_Arbiter/rr.v
module round_robin #(parameter N=4)(input clk, input rst, input [N-1:0]req,output reg [N-1:0]grant);
reg [$clog2(N)-1:0]pointer;
integer i;
integer index;
reg found;
always @(posedge clk)
begin
    if(rst)
    begin
        pointer<=0;
        grant<=0;
    end
    else
    begin
        grant<=0;
        found=0;
        for(i=0;i<N;i=i+1)
        begin
            index=(pointer + i)%N;
            if(req[index] && !found)
            begin
                grant[index]<=1;
                pointer<=(index +1)%N;
                found=1;
            end

        end
    end
end
endmodule

Round_Robin_Arbiter/rr_tb.v
`timescale 1ns/1ps
module round_robin_tb;
parameter N=4;
reg clk;
reg rst;
reg [N-1:0]req;
wire [N-1:0]grant;
round_robin #(N) uut (.clk(clk),.rst(rst),.req(req),.grant(grant));
always #5 clk=~clk;
initial begin
    $monitor("Time=%0t rst=%0b req=%0b grant=%0b",$time,rst,req,grant);
end
initial begin
    clk=0;
    rst=1;
    req=4'b0000;
    #12;
    rst=0;
    #10;
    req=4'b0000;
    #10;
    req=4'b0001;
    #10;
    req=4'b0101;
    #10;
    req=4'b1111;
    #40;
    req=4'b0110;
    #40;
    req=4'b0000;
    #20;
    $finish;
end
initial begin
    $dumpfile("rr_tb.vcd");
    $dumpvars(0,round_robin_tb);
end
endmodule

Round_Robin_Arbiter/rr_tb.vcd
$date
	Wed Jul 08 21:54:15 2026
$end
$version
	Icarus Verilog
$end
$timescale
	1ps
$end
$scope module round_robin_tb $end
$var wire 4 ! grant [3:0] $end
$var reg 1 " clk $end
$var reg 4 # req [3:0] $end
$var reg 1 $ rst $end
$scope module uut $end
$var wire 1 " clk $end
$var wire 4 % req [3:0] $end
$var wire 1 $ rst $end
$var reg 1 & found $end
$var reg 4 ' grant [3:0] $end
$var reg 2 ( pointer [1:0] $end
$var integer 32 ) i [31:0] $end
$var integer 32 * index [31:0] $end
$upscope $end
$upscope $end
$enddefinitions $end
#0
$dumpvars
bx *
bx )
bx (
bx '
x&
b0 %
1$
b0 #
0"
bx !
$end
#5000
b0 !
b0 '
b0 (
1"
#10000
0"
#12000
0$
#15000
b11 *
b100 )
0&
1"
#20000
0"
#25000
b11 *
b100 )
1"
#30000
0"
#32000
b1 #
b1 %
#35000
b1 (
b1 !
b1 '
1&
b11 *
b100 )
1"
#40000
0"
#42000
b101 #
b101 %
#45000
b11 (
b100 !
b100 '
b0 *
b100 )
1&
1"
#50000
0"
#52000
b1111 #
b1111 %
#55000
b0 (
b1000 !
b1000 '
b10 *
b100 )
1&
1"
#60000
0"
#65000
b1 (
b1 !
b1 '
b11 *
b100 )
1&
1"
#70000
0"
#75000
b10 (
b10 !
b10 '
b0 *
b100 )
1&
1"
#80000
0"
#85000
b11 (
b100 !
b100 '
b1 *
b100 )
1&
1"
#90000
0"
#92000
b110 #
b110 %
#95000
b10 (
b10 !
b10 '
b10 *
b100 )
1&
1"
#100000
0"
#105000
b11 (
b100 !
b100 '
b1 *
b100 )
1&
1"
#110000
0"
#115000
b10 (
b10 !
b10 '
b10 *
b100 )
1&
1"
#120000
0"
#125000
b11 (
b100 !
b100 '
b1 *
b100 )
1&
1"
#130000
0"
#132000
b0 #
b0 %
#135000
b0 !
b0 '
b10 *
b100 )
0&
1"
#140000
0"
#145000
b10 *
b100 )
1"
